 [
    {
  "japanese": "か",
  "romaji": "ka",
  "x": 0,
  "y": 0
  }, {
  "japanese": "が",
  "romaji": "ga",
  "x": 0,
  "y": 0
  }, {
  "japanese": "き",
  "romaji": "ki",
  "x": 0,
  "y": 0
  }, {
  "japanese": "ぎ",
  "romaji": "gi",
  "x": 0,
  "y": 0
  }, {
  "japanese": "く",
  "romaji": "ku",
  "x": 0,
  "y": 0
  }, {
  "japanese": "ぐ",
  "romaji": "gu",
  "x": 0,
  "y": 0
  }, {
  "japanese": "け",
  "romaji": "ke",
  "x": 0,
  "y": 0
  }, {
  "japanese": "げ",
  "romaji": "ge",
  "x": 0,
  "y": 0
  }, {
  "japanese": "こ",
  "romaji": "ko",
  "x": 0,
  "y": 0
  }, {
  "japanese": "ご",
  "romaji": "go",
  "x": 0,
  "y": 0
  }
]